MANIFEST.in
README.rst
setup.py
django_shop_ajax.egg-info/PKG-INFO
django_shop_ajax.egg-info/SOURCES.txt
django_shop_ajax.egg-info/dependency_links.txt
django_shop_ajax.egg-info/not-zip-safe
django_shop_ajax.egg-info/requires.txt
django_shop_ajax.egg-info/top_level.txt
shop_ajax/__init__.py
shop_ajax/models.py
shop_ajax/static/shop_ajax/shop.js