Metadata-Version: 1.0
Name: django-shop-ajax
Version: 0.1.3
Summary: Ajax utilities for django SHOP
Home-page: http://www.django-shop.org/
Author: Ales Kocjancic
Author-email: ales.kocjancic@divio.ch
License: BSD License
Platform: OS Independent
